CONTRIBUTING.rst
HISTORY.rst
LICENSE
MANIFEST.in
README.rst
setup.cfg
setup.py
docs/Makefile
docs/conf.py
docs/configtree.rst
docs/contributing.rst
docs/examples.rst
docs/history.rst
docs/index.rst
docs/make.bat
docs/module-base.rst
docs/module-device.rst
docs/module-errors.rst
docs/module-firewall.rst
docs/module-ha.rst
docs/module-network.rst
docs/module-objects.rst
docs/module-panorama.rst
docs/module-policies.rst
docs/module-predefined.rst
docs/module-updater.rst
docs/module-userid.rst
docs/readme.rst
docs/reference.rst
docs/usage.rst
pandevice/__init__.py
pandevice/base.py
pandevice/device.py
pandevice/errors.py
pandevice/firewall.py
pandevice/ha.py
pandevice/network.py
pandevice/objects.py
pandevice/panorama.py
pandevice/policies.py
pandevice/predefined.py
pandevice/updater.py
pandevice/userid.py
pandevice.egg-info/PKG-INFO
pandevice.egg-info/SOURCES.txt
pandevice.egg-info/dependency_links.txt
pandevice.egg-info/not-zip-safe
pandevice.egg-info/requires.txt
pandevice.egg-info/top_level.txt
tests/__init__.py
tests/test_PanOScomp.py
tests/test_base.py
tests/test_classic_objects.py
tests/test_firewall.py
tests/test_init.py
tests/test_integration.py
tests/test_userid.py
tests/test_versioning.py
tests/test_vsys_xpaths.py
tests/live/__init__.py
tests/live/conftest.py
tests/live/test_device_config.py
tests/live/test_network.py
tests/live/test_objects.py
tests/live/test_set_reference.py
tests/live/test_userid.py
tests/live/testlib.py