Metadata-Version: 1.1
Name: pandevice
Version: 0.11.0
Summary: Framework for interacting with Palo Alto Networks devices via API
Home-page: https://github.com/PaloAltoNetworks/pandevice
Author: Palo Alto Networks
Author-email: techpartners@paloaltonetworks.com
License: ISC
Keywords: pandevice
Platform: UNKNOWN
Classifier: Development Status :: 3 - Alpha
Classifier: Intended Audience :: Developers
Classifier: License :: OSI Approved :: ISC License (ISCL)
Classifier: Natural Language :: English
Classifier: Programming Language :: Python :: 2
Classifier: Programming Language :: Python :: 2.7
Classifier: Programming Language :: Python :: 3
Classifier: Programming Language :: Python :: 3.5
Classifier: Programming Language :: Python :: 3.6
